slipper.py
slipper-0.4.1.dist-info/METADATA
slipper-0.4.1.dist-info/RECORD
slipper-0.4.1.dist-info/WHEEL
slipper-0.4.1.dist-info/top_level.txt
